sqlalchemy_schema/__init__.py
sqlalchemy_schema/command/__init__.py
sqlalchemy_schema/command/driver.py
sqlalchemy_schema/command/main.py
sqlalchemy_schema/command/transformer.py
sqlalchemy_schema/decisions.py
sqlalchemy_schema/exceptions.py
sqlalchemy_schema/schema_factory.py
sqlalchemy_schema/types.py
sqlalchemy_schema/utils/__init__.py
sqlalchemy_schema/utils/format.py
sqlalchemy_schema/utils/imports.py
sqlalchemy_schema/walkers.py
sqlalchemy_schema-0.1.1.dist-info/LICENSE
sqlalchemy_schema-0.1.1.dist-info/METADATA
sqlalchemy_schema-0.1.1.dist-info/WHEEL
sqlalchemy_schema-0.1.1.dist-info/entry_points.txt
sqlalchemy_schema-0.1.1.dist-info/RECORD
