Metadata-Version: 2.3
Name: sqlalchemy-schema
Version: 0.1.1
Summary: Convert SQLAlchemy models to JSON Schema definitions
License: MIT
Author: Daniele Esposti
Author-email: daniele.esposti@gmail.com
Requires-Python: >=3.10,<4.0
Classifier: License :: OSI Approved :: MIT License
Classifier: Programming Language :: Python :: 3
Classifier: Programming Language :: Python :: 3.10
Classifier: Programming Language :: Python :: 3.11
Classifier: Programming Language :: Python :: 3.12
Classifier: Programming Language :: Python :: 3.13
Requires-Dist: click (>=8.1)
Requires-Dist: jsonschema (>=4.23)
Requires-Dist: loguru (>=0.7)
Requires-Dist: pyyaml (>=5.4)
Requires-Dist: sqlalchemy (>=2.0)
